<?xml version="1.0" encoding="utf-8" ?>
<dwsync>
<file name="LICENSE" server="192.168.1.8" local="130924167520000000" remote="130924167520000000" Dst="0" />
<file name="class.phpmailer.php" server="192.168.1.8" local="130924167500000000" remote="130924167500000000" Dst="0" />
<file name="class.smtp.php" server="192.168.1.8" local="130924167500000000" remote="130924167500000000" Dst="0" />
<file name="composer.json" server="192.168.1.8" local="130924167500000000" remote="130924167500000000" Dst="0" />
<file name="changelog.md" server="192.168.1.8" local="130924167500000000" remote="130924167500000000" Dst="0" />
<file name="README.md" server="192.168.1.8" local="130924167520000000" remote="130924167520000000" Dst="0" />
<file name="VERSION" server="192.168.1.8" local="130924167520000000" remote="130924167520000000" Dst="0" />
<file name="PHPMailerAutoload.php" server="192.168.1.8" local="130924167520000000" remote="130924167520000000" Dst="0" />
<file name="class.pop3.php" server="192.168.1.8" local="130924167500000000" remote="130924167500000000" Dst="0" />
<file name=".gitignore" server="192.168.1.8" local="130924167490000000" remote="130924167490000000" Dst="0" />
<file name="travis.phpunit.xml.dist" server="192.168.1.8" local="130924167520000000" remote="130924167520000000" Dst="0" />
</dwsync>